ogpy/__init__.py
ogpy/console.py
ogpy/parser.py
ogpy/py.typed
ogpy/types.py
ogpy/adapters/__init__.py
ogpy/adapters/sphinx.py
ogpy/client/__init__.py
ogpy/client/browser.py
ogpy-0.2.0.dist-info/METADATA
ogpy-0.2.0.dist-info/WHEEL
ogpy-0.2.0.dist-info/entry_points.txt
ogpy-0.2.0.dist-info/licenses/LICENSE
ogpy-0.2.0.dist-info/RECORD
