Metadata-Version: 2.4
Name: OGPy
Version: 0.2.0
Summary: Modern consumer of Open Graph protocol
Project-URL: Home, https://github.com/atakei-lab/OGPy/
Project-URL: Documentation, https://ogpy.readthedocs.io/stable/
Project-URL: Repository, https://github.com/atakei-lab/OGPy/
Author-email: Kazuya Takei <myself@attakei.net>
License-File: LICENSE
Classifier: Development Status :: 3 - Alpha
Classifier: Environment :: Console
Classifier: License :: OSI Approved
Classifier: License :: OSI Approved :: Apache Software License
Classifier: Operating System :: OS Independent
Classifier: Programming Language :: Python
Classifier: Programming Language :: Python :: 3
Classifier: Programming Language :: Python :: 3 :: Only
Classifier: Programming Language :: Python :: 3.10
Classifier: Programming Language :: Python :: 3.11
Classifier: Programming Language :: Python :: 3.12
Classifier: Programming Language :: Python :: 3.13
Classifier: Topic :: Software Development
Classifier: Topic :: Software Development :: Libraries
Classifier: Topic :: Software Development :: Libraries :: Python Modules
Classifier: Topic :: Utilities
Requires-Python: >=3.10
Requires-Dist: beautifulsoup4>=4.0
Requires-Dist: httpx>=0.24.0
Provides-Extra: browser
Requires-Dist: playwright>=1.51.0; extra == 'browser'
Provides-Extra: sphinx
Requires-Dist: sphinx>=7.0; extra == 'sphinx'
